FuliyeBianhuanJiqiYingyongSitanfudaxue/README.md
FuliyeBianhuanJiqiYingyongSitanfudaxue/__init__.py
FuliyeBianhuanJiqiYingyongSitanfudaxue/__main__.py
FuliyeBianhuanJiqiYingyongSitanfudaxue/file.pdf
FuliyeBianhuanJiqiYingyongSitanfudaxue/index.html
fuliye_bianhuan_jiqi_yingyong_sitanfudaxue-2024.3.3.0.dist-info/METADATA
fuliye_bianhuan_jiqi_yingyong_sitanfudaxue-2024.3.3.0.dist-info/WHEEL
fuliye_bianhuan_jiqi_yingyong_sitanfudaxue-2024.3.3.0.dist-info/entry_points.txt
fuliye_bianhuan_jiqi_yingyong_sitanfudaxue-2024.3.3.0.dist-info/top_level.txt
fuliye_bianhuan_jiqi_yingyong_sitanfudaxue-2024.3.3.0.dist-info/RECORD
